Package/Base.py
Package/__init__.py
SalKikal-0.1.0.dist-info/METADATA
SalKikal-0.1.0.dist-info/WHEEL
SalKikal-0.1.0.dist-info/top_level.txt
SalKikal-0.1.0.dist-info/RECORD
