Metadata-Version: 2.1
Name: SalKikal
Version: 0.1.0
Summary: A package for creating and modifying class objects
Author: Salome Kikalishvili
Author-email: salomekikalishvili2000@gmail.com
